mcpssh/__init__.py
mcpssh/main.py
mcpssh/mcpssh-wrapper.py
mcpssh/query_passman.py
ssh_mcp-0.1.4.dist-info/METADATA
ssh_mcp-0.1.4.dist-info/WHEEL
ssh_mcp-0.1.4.dist-info/entry_points.txt
ssh_mcp-0.1.4.dist-info/RECORD
