Metadata-Version: 2.4
Name: ssh-mcp
Version: 0.1.4
Summary: SSH MCP - tools for remote SSH operations for debugging
Author-email: czyhandsome <czyhandsome@foxmail.com>
License: MIT
Keywords: mcp,protocol,remote,server,ssh
Requires-Python: >=3.12
Requires-Dist: mcp-python>=0.1.4
Requires-Dist: paramiko>=3.4.0
Requires-Dist: requests
